pantea/__init__.py
pantea/_version.py
pantea/config.py
pantea/logger.py
pantea/pytree.py
pantea/types.py
pantea/units.py
pantea/atoms/__init__.py
pantea/atoms/box.py
pantea/atoms/distance.py
pantea/atoms/element.py
pantea/atoms/neighbor.py
pantea/atoms/structure.py
pantea/datasets/__init__.py
pantea/datasets/dataset.py
pantea/datasets/runner.py
pantea/descriptors/__init__.py
pantea/descriptors/scaler.py
pantea/descriptors/acsf/__init__.py
pantea/descriptors/acsf/acsf.py
pantea/descriptors/acsf/angular.py
pantea/descriptors/acsf/cutoff.py
pantea/descriptors/acsf/radial.py
pantea/descriptors/acsf/symmetry.py
pantea/models/__init__.py
pantea/models/nn/__init__.py
pantea/models/nn/activation.py
pantea/models/nn/initializer.py
pantea/models/nn/model.py
pantea/potentials/__init__.py
pantea/potentials/nnp/__init__.py
pantea/potentials/nnp/atomic_potential.py
pantea/potentials/nnp/energy.py
pantea/potentials/nnp/force.py
pantea/potentials/nnp/gradient_descent.py
pantea/potentials/nnp/kalman_filter.py
pantea/potentials/nnp/metrics.py
pantea/potentials/nnp/potential.py
pantea/potentials/nnp/settings.py
pantea/potentials/nnp/trainer.py
pantea/simulation/__init__.py
pantea/simulation/lennard_jones.py
pantea/simulation/molecular_dynamics.py
pantea/simulation/monte_carlo.py
pantea/simulation/simulate.py
pantea/simulation/system.py
pantea/simulation/thermostat.py
pantea/utils/__init__.py
pantea/utils/attribute.py
pantea/utils/batch.py
pantea/utils/compare.py
pantea/utils/profiler.py
pantea/utils/tokenize.py
pantea-0.11.0.dist-info/AUTHORS.rst
pantea-0.11.0.dist-info/LICENSE
pantea-0.11.0.dist-info/METADATA
pantea-0.11.0.dist-info/WHEEL
pantea-0.11.0.dist-info/entry_points.txt
pantea-0.11.0.dist-info/top_level.txt
pantea-0.11.0.dist-info/RECORD
