Metadata-Version: 2.1
Name: pantea
Version: 0.11.0
Summary: A Python package for developing machine learning interatomic potentials, based on JAX.
Home-page: https://github.com/hghcomphys/pantea
Author: Hossein Ghorbanfekr
Author-email: hgh.comphys@gmail.com
License: GNU General Public License v3
Keywords: pantea
Classifier: Development Status :: 2 - Pre-Alpha
Classifier: Intended Audience :: Developers
Classifier: License :: OSI Approved :: GNU General Public License v3 (GPLv3)
Classifier: Natural Language :: English
Classifier: Programming Language :: Python :: 3.8
Requires-Python: >=3.8
License-File: LICENSE
License-File: AUTHORS.rst
Requires-Dist: Click>=7.0
Requires-Dist: tqdm>=4.6
Requires-Dist: ase>=3.2
Requires-Dist: frozendict>=2.3
Requires-Dist: flax>=0.6
Requires-Dist: pydantic>=1.10
Requires-Dist: pandas>=1.5.3
